jawad/__init__.py
jawad/calculator.py
jawad-1.0.0.dist-info/LICENSE
jawad-1.0.0.dist-info/METADATA
jawad-1.0.0.dist-info/WHEEL
jawad-1.0.0.dist-info/top_level.txt
jawad-1.0.0.dist-info/RECORD
