Metadata-Version: 2.1
Name: jawad
Version: 1.0.0
Summary: My package description
Author-email: Josiah Carberry <josiah_carberry@brown.edu>
License: GNU GENERAL PUBLIC LICENSE
Classifier: Framework :: Chandler
Classifier: Programming Language :: Python :: 3
Classifier: Development Status :: 1 - Planning
Requires-Python: >=3.1
License-File: LICENSE
